getpublicip/__init__.py
getpublicip/getpublicip.py
getpublicip-1.0.1.dist-info/METADATA
getpublicip-1.0.1.dist-info/WHEEL
getpublicip-1.0.1.dist-info/entry_points.txt
getpublicip-1.0.1.dist-info/top_level.txt
getpublicip-1.0.1.dist-info/RECORD
