Metadata-Version: 2.2
Name: getpublicip
Version: 1.0.1
Summary: A package for fetching public ip
Home-page: https://github.com/jayaramyalla/publicip
Author: jayaram yalla
Author-email: jayaram@duck.com
Classifier: Programming Language :: Python :: 3
Classifier: License :: OSI Approved :: MIT License
Classifier: Operating System :: OS Independent
Requires-Python: >=3.6
Requires-Dist: requests
Requires-Dist: colorama
Dynamic: author
Dynamic: author-email
Dynamic: classifier
Dynamic: description
Dynamic: description-content-type
Dynamic: home-page
Dynamic: requires-dist
Dynamic: requires-python
Dynamic: summary
